makeme/__init__.py
makeme/command_line.py
tests/test_target_matching.py
MakeMe-0.2.4.dist-info/LICENSE
MakeMe-0.2.4.dist-info/METADATA
MakeMe-0.2.4.dist-info/WHEEL
MakeMe-0.2.4.dist-info/entry_points.txt
MakeMe-0.2.4.dist-info/top_level.txt
MakeMe-0.2.4.dist-info/RECORD
