Metadata-Version: 2.1
Name: MakeMe
Version: 0.2.4
Summary: Easing the usage of Makefiles
Home-page: https://github.com/OakNinja/MakeMe
Author: Esse Woods
Author-email: esse.woods@gmail.com
License: UNKNOWN
Project-URL: Bug Tracker, https://github.com/OakNinja/makeme/issues
Project-URL: Documentation, https://github.com/OakNinja/MakeMe
Project-URL: Source Code, https://github.com/OakNinja/MakeMe
Keywords: Makefile MakeMe MM
Platform: UNKNOWN
Classifier: Programming Language :: Python :: 3
Classifier: License :: OSI Approved :: MIT License
Classifier: Development Status :: 3 - Alpha
Classifier: Operating System :: OS Independent
Classifier: Topic :: Utilities
Requires-Python: >=3.6
Requires-Dist: questionary
